bufap/__init__.py
bufap/_version.py
bufap/common.py
bufap/conf.py
bufap/ouilookup.json
bufap/ssh.py
bufap/tool.py
bufap/cli/__init__.py
bufap/cli/bufap-cli.spec
bufap/gui/__init__.py
bufap/gui/bufap-gui.py
bufap/gui/bufap-gui.spec
bufap/gui/control.py
bufap/gui/logic.py
bufap/gui/samples.py
bufap/gui/views.py
bufap/parser/__init__.py
bufap/parser/airset.py
bufap/parser/bridge.py
bufap/parser/ether.py
bufap/parser/ip.py
bufap/parser/radius.py
bufap/parser/setup.py
bufap-2.3.0.dist-info/METADATA
bufap-2.3.0.dist-info/WHEEL
bufap-2.3.0.dist-info/entry_points.txt
bufap-2.3.0.dist-info/RECORD
