Metadata-Version: 2.1
Name: bufap
Version: 2.3.0
Summary: A Python module (and CLI/GUI tool) for managing Buffalo wireless access points.
Author-email: Masumitsu Hatta <Masumitsu.Hatta@gmail.com>
Requires-Python: >=3.9
Requires-Dist: dictknife>=0.14.0
Requires-Dist: ouilookup>=0.3.1
Requires-Dist: paramiko>=3.2.0
